pyaff4/__init__.py
pyaff4/_version.py
pyaff4/abort_test.py
pyaff4/aes_keywrap.py
pyaff4/aff4.py
pyaff4/aff4_cloud.py
pyaff4/aff4_directory.py
pyaff4/aff4_directory_test.py
pyaff4/aff4_file.py
pyaff4/aff4_image.py
pyaff4/aff4_image_test.py
pyaff4/aff4_image_test2.py
pyaff4/aff4_imager_utils.py
pyaff4/aff4_map.py
pyaff4/aff4_map_test.py
pyaff4/aff4_metadata.py
pyaff4/aff4_utils.py
pyaff4/block_hasher.py
pyaff4/container.py
pyaff4/container_test.py
pyaff4/crypt_image_test.py
pyaff4/data_store.py
pyaff4/data_store_test.py
pyaff4/dedup_test.py
pyaff4/encrypted_stream.py
pyaff4/encryptedstream_test.py
pyaff4/escaping.py
pyaff4/escaping_test.py
pyaff4/hashes.py
pyaff4/hashing_test.py
pyaff4/hexdump.py
pyaff4/keybag.py
pyaff4/lexicon.py
pyaff4/linear_hasher.py
pyaff4/logical.py
pyaff4/logical_append_test.py
pyaff4/logical_test.py
pyaff4/plugins.py
pyaff4/random_imagestream_test.py
pyaff4/rdfvalue.py
pyaff4/rdfvalue_test.py
pyaff4/reference_test.py
pyaff4/registry.py
pyaff4/standards_test.py
pyaff4/statx.py
pyaff4/stream_factory.py
pyaff4/stream_test.py
pyaff4/streams.py
pyaff4/struct_parser.py
pyaff4/symbolic_streams.py
pyaff4/test_crypto.py
pyaff4/turtle.py
pyaff4/utils.py
pyaff4/version.py
pyaff4/zip.py
pyaff4/zip_test.py
pyaff4/zip_test_extended.py
pyaff4/zip_test_unicode.py
pyaff4/zip_test_unicode2.py
pyaff4-0.34.dist-info/LICENSE
pyaff4-0.34.dist-info/METADATA
pyaff4-0.34.dist-info/WHEEL
pyaff4-0.34.dist-info/top_level.txt
pyaff4-0.34.dist-info/RECORD
