Metadata-Version: 2.1
Name: pyaff4
Version: 0.34
Summary: Advanced Forensic Format Version 4 (AFF4) Python module.
Home-page: https://www.aff4.org/
Author: Michael Cohen, Bradley Schatz
Author-email: scudette@gmail.com, bradley@evimetry.com
License: UNKNOWN
Platform: UNKNOWN
License-File: LICENSE
Requires-Dist: future (==0.17.1)
Requires-Dist: aff4-snappy (==0.5.1)
Requires-Dist: rdflib[sparql] (==4.2.2)
Requires-Dist: intervaltree (==2.1.0)
Requires-Dist: pyyaml (==5.4)
Requires-Dist: tzlocal (==2.1)
Requires-Dist: html5lib (==1.0.1)
Requires-Dist: python-dateutil (==2.8.0)
Requires-Dist: fastchunking (==0.0.3)
Requires-Dist: hexdump
Requires-Dist: pynacl
Requires-Dist: pycryptodome
Requires-Dist: pycryptoplus
Requires-Dist: aes-keywrap
Requires-Dist: passlib
Requires-Dist: cryptography
Requires-Dist: expiringdict
Requires-Dist: lz4
Provides-Extra: cloud
Requires-Dist: google-api-python-client ; extra == 'cloud'
